django_annotated_property/__init__.py
django_annotated_property/annotated_property.py
django_annotated_property-0.1.0.dist-info/licenses/LICENCE
django_annotated_property-0.1.0.dist-info/METADATA
django_annotated_property-0.1.0.dist-info/WHEEL
django_annotated_property-0.1.0.dist-info/top_level.txt
django_annotated_property-0.1.0.dist-info/RECORD
