Metadata-Version: 2.4
Name: django-annotated-property
Version: 0.1.0
Summary: Decorator for Django model properties that checks if an annotation exists on the instance.
Home-page: https://github.com/milano-slesarik/django-annotated-property
Author: Milan Slesarik
Author-email: milslesarik@gmail.com
Classifier: Framework :: Django
Classifier: Programming Language :: Python :: 3
Classifier: License :: OSI Approved :: MIT License
Requires-Python: >=3.6
License-File: LICENCE
Requires-Dist: Django>=2.2
Dynamic: author
Dynamic: author-email
Dynamic: classifier
Dynamic: description
Dynamic: description-content-type
Dynamic: home-page
Dynamic: license-file
Dynamic: requires-dist
Dynamic: requires-python
Dynamic: summary
